werkzeug/__init__.py
werkzeug/_internal.py
werkzeug/_reloader.py
werkzeug/datastructures.py
werkzeug/datastructures.pyi
werkzeug/exceptions.py
werkzeug/formparser.py
werkzeug/http.py
werkzeug/local.py
werkzeug/py.typed
werkzeug/security.py
werkzeug/serving.py
werkzeug/test.py
werkzeug/testapp.py
werkzeug/urls.py
werkzeug/user_agent.py
werkzeug/utils.py
werkzeug/wsgi.py
werkzeug/debug/__init__.py
werkzeug/debug/console.py
werkzeug/debug/repr.py
werkzeug/debug/tbtools.py
werkzeug/debug/shared/ICON_LICENSE.md
werkzeug/debug/shared/console.png
werkzeug/debug/shared/debugger.js
werkzeug/debug/shared/less.png
werkzeug/debug/shared/more.png
werkzeug/debug/shared/style.css
werkzeug/middleware/__init__.py
werkzeug/middleware/dispatcher.py
werkzeug/middleware/http_proxy.py
werkzeug/middleware/lint.py
werkzeug/middleware/profiler.py
werkzeug/middleware/proxy_fix.py
werkzeug/middleware/shared_data.py
werkzeug/routing/__init__.py
werkzeug/routing/converters.py
werkzeug/routing/exceptions.py
werkzeug/routing/map.py
werkzeug/routing/matcher.py
werkzeug/routing/rules.py
werkzeug/sansio/__init__.py
werkzeug/sansio/http.py
werkzeug/sansio/multipart.py
werkzeug/sansio/request.py
werkzeug/sansio/response.py
werkzeug/sansio/utils.py
werkzeug/wrappers/__init__.py
werkzeug/wrappers/request.py
werkzeug/wrappers/response.py
werkzeug_patched-2.2.5.dist-info/licenses/LICENSE.rst
werkzeug_patched-2.2.5.dist-info/METADATA
werkzeug_patched-2.2.5.dist-info/WHEEL
werkzeug_patched-2.2.5.dist-info/top_level.txt
werkzeug_patched-2.2.5.dist-info/RECORD
