Metadata-Version: 2.4
Name: Werkzeug-patched
Version: 2.2.5
Summary: The comprehensive WSGI web application library.
Home-page: https://palletsprojects.com/p/werkzeug/
Author: Armin Ronacher
Author-email: armin.ronacher@active-4.com
Maintainer: Pallets
Maintainer-email: contact@palletsprojects.com
License: BSD-3-Clause
Project-URL: Donate, https://palletsprojects.com/donate
Project-URL: Documentation, https://werkzeug.palletsprojects.com/
Project-URL: Changes, https://werkzeug.palletsprojects.com/changes/
Project-URL: Source Code, https://github.com/pallets/werkzeug/
Project-URL: Issue Tracker, https://github.com/pallets/werkzeug/issues/
Project-URL: Twitter, https://twitter.com/PalletsTeam
Project-URL: Chat, https://discord.gg/pallets
Classifier: Development Status :: 5 - Production/Stable
Classifier: Environment :: Web Environment
Classifier: Intended Audience :: Developers
Classifier: License :: OSI Approved :: BSD License
Classifier: Operating System :: OS Independent
Classifier: Programming Language :: Python
Classifier: Topic :: Internet :: WWW/HTTP :: Dynamic Content
Classifier: Topic :: Internet :: WWW/HTTP :: WSGI
Classifier: Topic :: Internet :: WWW/HTTP :: WSGI :: Application
Classifier: Topic :: Internet :: WWW/HTTP :: WSGI :: Middleware
Classifier: Topic :: Software Development :: Libraries :: Application Frameworks
Requires-Python: >=3.7
License-File: LICENSE.rst
Requires-Dist: MarkupSafe>=2.1.1
Provides-Extra: watchdog
Requires-Dist: watchdog; extra == "watchdog"
Dynamic: license-file
Dynamic: provides-extra
Dynamic: requires-dist
